sangwoo_lotto/__init__.py
sangwoo_lotto/draw.py
sangwoo_lotto-0.2.0.dist-info/METADATA
sangwoo_lotto-0.2.0.dist-info/WHEEL
sangwoo_lotto-0.2.0.dist-info/top_level.txt
sangwoo_lotto-0.2.0.dist-info/RECORD
