Metadata-Version: 2.1
Name: sangwoo_lotto
Version: 0.2.0
Summary: Default template for PDM package
Author-email: GITSangWoo <dogcenta@gmail.com>
License: MIT
Requires-Python: >=3.9
